honeybee/__init__.py
honeybee/loaders/__init__.py
honeybee/loaders/Radiology/__init__.py
honeybee/loaders/Radiology/dataset.py
honeybee/loaders/Radiology/loader.py
honeybee/loaders/Radiology/metadata.py
honeybee/loaders/Radiology/radiology.py
honeybee/loaders/Reader/mindsDBreader.py
honeybee/loaders/Reader/reader.py
honeybee/loaders/Scans/scan.py
honeybee/loaders/Slide/__init__.py
honeybee/loaders/Slide/slide.py
honeybee/models/__init__.py
honeybee/models/HuggingFaceEmbedder/embedder.py
honeybee/models/LlamaEmbedder/__init__.py
honeybee/models/LlamaEmbedder/llama_embedder.py
honeybee/models/REMEDIS/remedis.py
honeybee/models/RadImageNet/__init__.py
honeybee/models/RadImageNet/radimagenet.py
honeybee/models/TissueDetector/tissue_detector.py
honeybee/models/UNI/uni.py
honeybee/models/UNI2/__init__.py
honeybee/models/UNI2/uni2.py
honeybee/models/Virchow2/__init__.py
honeybee/models/Virchow2/virchow2.py
honeybee/models/Virchow2/virchow2_simple.py
honeybee/processors/__init__.py
honeybee/processors/clinical_processor.py
honeybee/processors/pathology_processor.py
honeybee/processors/radiology_processor.py
honeybee/processors/radiology/__init__.py
honeybee/processors/radiology/preprocessing.py
honeybee/processors/radiology/processor.py
honeybee/processors/radiology/segmentation.py
honeybee/processors/wsi/__init__.py
honeybee/processors/wsi/stain_normalization.py
honeybee/processors/wsi/stain_normalization_fixed.py
honeybee/processors/wsi/stain_normalization_working.py
honeybee/processors/wsi/stain_separation.py
honeybee/processors/wsi/tissue_detection.py
honeybee/utils/__init__.py
honeybee/utils/pydantic_compat.py
honeybee_ml-0.1.0.dist-info/licenses/LICENSE
honeybee_ml-0.1.0.dist-info/METADATA
honeybee_ml-0.1.0.dist-info/WHEEL
honeybee_ml-0.1.0.dist-info/top_level.txt
honeybee_ml-0.1.0.dist-info/RECORD
