Metadata-Version: 2.4
Name: honeybee-ml
Version: 0.1.0
Summary: A Scalable Modular Framework for Multimodal AI in Oncology
Author-email: Aakash Tripathi <aakash.tripathi@moffitt.org>, Lab Rasool <ghulam.rasool@moffitt.org>
Maintainer-email: Aakash Tripathi <aakash.tripathi@moffitt.org>
License-Expression: MIT
Project-URL: Homepage, https://github.com/lab-rasool/HoneyBee
Project-URL: Documentation, https://lab-rasool.github.io/HoneyBee/
Project-URL: Repository, https://github.com/lab-rasool/HoneyBee
Project-URL: Bug Tracker, https://github.com/lab-rasool/HoneyBee/issues
Project-URL: Paper, https://arxiv.org/abs/2405.07460
Keywords: multimodal AI,oncology,cancer research,medical imaging,clinical NLP,machine learning,pathology,radiology,biomedical,healthcare
Classifier: Development Status :: 3 - Alpha
Classifier: Intended Audience :: Science/Research
Classifier: Intended Audience :: Healthcare Industry
Classifier: Programming Language :: Python :: 3
Classifier: Programming Language :: Python :: 3.8
Classifier: Programming Language :: Python :: 3.9
Classifier: Programming Language :: Python :: 3.10
Classifier: Programming Language :: Python :: 3.11
Classifier: Programming Language :: Python :: 3.12
Classifier: Topic :: Scientific/Engineering :: Artificial Intelligence
Classifier: Topic :: Scientific/Engineering :: Medical Science Apps.
Classifier: Topic :: Scientific/Engineering :: Image Recognition
Classifier: Topic :: Text Processing :: Linguistic
Classifier: Operating System :: OS Independent
Requires-Python: >=3.8
License-File: LICENSE
Requires-Dist: numpy>=1.20.0
Requires-Dist: pandas>=1.3.0
Requires-Dist: torch>=2.0.0
Requires-Dist: torchvision>=0.15.0
Requires-Dist: torchaudio>=2.0.0
Requires-Dist: transformers>=4.30.0
Requires-Dist: accelerate>=0.20.0
Requires-Dist: bitsandbytes>=0.40.0
Requires-Dist: scikit-image>=0.19.0
Requires-Dist: scipy>=1.7.0
Requires-Dist: matplotlib>=3.3.0
Requires-Dist: imageio>=2.9.0
Provides-Extra: clinical
Requires-Dist: llama-index>=0.9.0; extra == "clinical"
Requires-Dist: langchain>=0.1.0; extra == "clinical"
Requires-Dist: pytesseract>=0.3.8; extra == "clinical"
Requires-Dist: pdf2image>=1.16.0; extra == "clinical"
Requires-Dist: PyPDF2>=3.0.0; extra == "clinical"
Provides-Extra: radiology
Requires-Dist: pydicom>=2.3.0; extra == "radiology"
Requires-Dist: SimpleITK>=2.2.0; extra == "radiology"
Requires-Dist: nibabel>=4.0.0; extra == "radiology"
Requires-Dist: opencv-python>=4.5.0; extra == "radiology"
Provides-Extra: pathology
Requires-Dist: openslide-python>=1.2.0; extra == "pathology"
Requires-Dist: colour-science>=0.4.0; extra == "pathology"
Requires-Dist: albumentations>=1.3.0; extra == "pathology"
Requires-Dist: cucim>=23.0.0; extra == "pathology"
Provides-Extra: molecular
Requires-Dist: pyarrow>=10.0.0; extra == "molecular"
Requires-Dist: fastparquet>=2023.0.0; extra == "molecular"
Provides-Extra: database
Requires-Dist: pymongo>=4.0.0; extra == "database"
Provides-Extra: dev
Requires-Dist: pytest>=7.0.0; extra == "dev"
Requires-Dist: pytest-cov>=4.0.0; extra == "dev"
Requires-Dist: black>=23.0.0; extra == "dev"
Requires-Dist: ruff>=0.1.0; extra == "dev"
Requires-Dist: mypy>=1.0.0; extra == "dev"
Provides-Extra: visualization
Requires-Dist: ipykernel>=6.0.0; extra == "visualization"
Requires-Dist: ipywidgets>=8.0.0; extra == "visualization"
Provides-Extra: models
Requires-Dist: timm>=0.9.0; extra == "models"
Requires-Dist: onnxruntime>=1.15.0; extra == "models"
Requires-Dist: peft>=0.5.0; extra == "models"
Provides-Extra: all
Requires-Dist: honeybee-ml[clinical,database,models,molecular,pathology,radiology,visualization]; extra == "all"
Dynamic: license-file
